{"nodes": [{"id": "src_planner_autoplanner_ts", "label": "autoPlanner.ts", "file_type": "code", "source_file": "src\\planner\\autoPlanner.ts", "source_location": "L1"}, {"id": "autoplanner_baselinerepgoal", "label": "baselineRepGoal()", "file_type": "code", "source_file": "src\\planner\\autoPlanner.ts", "source_location": "L94"}, {"id": "autoplanner_getroutinesessionlabel", "label": "getRoutineSessionLabel()", "file_type": "code", "source_file": "src\\planner\\autoPlanner.ts", "source_location": "L225"}, {"id": "autoplanner_getrecommendedroutinesfordays", "label": "getRecommendedRoutinesForDays()", "file_type": "code", "source_file": "src\\planner\\autoPlanner.ts", "source_location": "L240"}, {"id": "autoplanner_remapgzcltiers", "label": "remapGzclTiers()", "file_type": "code", "source_file": "src\\planner\\autoPlanner.ts", "source_location": "L256"}, {"id": "autoplanner_bodyregion", "label": "bodyRegion()", "file_type": "code", "source_file": "src\\planner\\autoPlanner.ts", "source_location": "L317"}, {"id": "autoplanner_normalizeexercisename", "label": "normalizeExerciseName()", "file_type": "code", "source_file": "src\\planner\\autoPlanner.ts", "source_location": "L321"}, {"id": "autoplanner_applygoalprescription", "label": "applyGoalPrescription()", "file_type": "code", "source_file": "src\\planner\\autoPlanner.ts", "source_location": "L325"}, {"id": "autoplanner_estimateexercisedurationseconds", "label": "estimateExerciseDurationSeconds()", "file_type": "code", "source_file": "src\\planner\\autoPlanner.ts", "source_location": "L340"}, {"id": "autoplanner_calcestimatedminutes", "label": "calcEstimatedMinutes()", "file_type": "code", "source_file": "src\\planner\\autoPlanner.ts", "source_location": "L353"}, {"id": "autoplanner_isuuidv4", "label": "isUuidV4()", "file_type": "code", "source_file": "src\\planner\\autoPlanner.ts", "source_location": "L362"}, {"id": "autoplanner_islikelyprimarycompound", "label": "isLikelyPrimaryCompound()", "file_type": "code", "source_file": "src\\planner\\autoPlanner.ts", "source_location": "L366"}, {"id": "autoplanner_normalizeroutinetype", "label": "normalizeRoutineType()", "file_type": "code", "source_file": "src\\planner\\autoPlanner.ts", "source_location": "L372"}, {"id": "autoplanner_normalizestoredroutinetype", "label": "normalizeStoredRoutineType()", "file_type": "code", "source_file": "src\\planner\\autoPlanner.ts", "source_location": "L400"}, {"id": "autoplanner_inferaxis", "label": "inferAxis()", "file_type": "code", "source_file": "src\\planner\\autoPlanner.ts", "source_location": "L408"}, {"id": "autoplanner_hassessiontag", "label": "hasSessionTag()", "file_type": "code", "source_file": "src\\planner\\autoPlanner.ts", "source_location": "L416"}, {"id": "autoplanner_filterbysessionrule", "label": "filterBySessionRule()", "file_type": "code", "source_file": "src\\planner\\autoPlanner.ts", "source_location": "L431"}, {"id": "autoplanner_dedupeexercisesbyid", "label": "dedupeExercisesById()", "file_type": "code", "source_file": "src\\planner\\autoPlanner.ts", "source_location": "L444"}, {"id": "autoplanner_dedupeplannedbyid", "label": "dedupePlannedById()", "file_type": "code", "source_file": "src\\planner\\autoPlanner.ts", "source_location": "L463"}, {"id": "autoplanner_buildvolumeexpansioncandidates", "label": "buildVolumeExpansionCandidates()", "file_type": "code", "source_file": "src\\planner\\autoPlanner.ts", "source_location": "L477"}, {"id": "autoplanner_classifyexpansionname", "label": "classifyExpansionName()", "file_type": "code", "source_file": "src\\planner\\autoPlanner.ts", "source_location": "L513"}, {"id": "autoplanner_classifyexpansioncandidate", "label": "classifyExpansionCandidate()", "file_type": "code", "source_file": "src\\planner\\autoPlanner.ts", "source_location": "L527"}, {"id": "autoplanner_buildcategoryexpansionqueue", "label": "buildCategoryExpansionQueue()", "file_type": "code", "source_file": "src\\planner\\autoPlanner.ts", "source_location": "L531"}, {"id": "autoplanner_expandfortimebudget", "label": "expandForTimeBudget()", "file_type": "code", "source_file": "src\\planner\\autoPlanner.ts", "source_location": "L574"}, {"id": "autoplanner_getblueprint", "label": "getBlueprint()", "file_type": "code", "source_file": "src\\planner\\autoPlanner.ts", "source_location": "L665"}, {"id": "autoplanner_getblueprintexercises", "label": "getBlueprintExercises()", "file_type": "code", "source_file": "src\\planner\\autoPlanner.ts", "source_location": "L675"}, {"id": "autoplanner_detectsessionindex", "label": "detectSessionIndex()", "file_type": "code", "source_file": "src\\planner\\autoPlanner.ts", "source_location": "L707"}, {"id": "autoplanner_picklowerbodysessionindex", "label": "pickLowerBodySessionIndex()", "file_type": "code", "source_file": "src\\planner\\autoPlanner.ts", "source_location": "L711"}, {"id": "autoplanner_tiercapfortime", "label": "tierCapForTime()", "file_type": "code", "source_file": "src\\planner\\autoPlanner.ts", "source_location": "L738"}, {"id": "autoplanner_getmaxexercisesfortime", "label": "getMaxExercisesForTime()", "file_type": "code", "source_file": "src\\planner\\autoPlanner.ts", "source_location": "L748"}, {"id": "autoplanner_buildcoreblueprintbytier", "label": "buildCoreBlueprintByTier()", "file_type": "code", "source_file": "src\\planner\\autoPlanner.ts", "source_location": "L764"}, {"id": "autoplanner_maprecentsetsbyexercise", "label": "mapRecentSetsByExercise()", "file_type": "code", "source_file": "src\\planner\\autoPlanner.ts", "source_location": "L786"}, {"id": "autoplanner_planexercisefromhistory", "label": "planExerciseFromHistory()", "file_type": "code", "source_file": "src\\planner\\autoPlanner.ts", "source_location": "L803"}, {"id": "autoplanner_planroutineworkoutpure", "label": "planRoutineWorkoutPure()", "file_type": "code", "source_file": "src\\planner\\autoPlanner.ts", "source_location": "L885"}, {"id": "autoplanner_runplannerpreflightaudit", "label": "runPlannerPreflightAudit()", "file_type": "code", "source_file": "src\\planner\\autoPlanner.ts", "source_location": "L1024"}, {"id": "autoplanner_generateworkout", "label": "generateWorkout()", "file_type": "code", "source_file": "src\\planner\\autoPlanner.ts", "source_location": "L1091"}], "edges": [{"source": "src_planner_autoplanner_ts", "target": "src_planner_db_schema", "relation": "imports_from", "confidence": "EXTRACTED", "source_file": "src\\planner\\autoPlanner.ts", "source_location": "L1", "weight": 1.0}, {"source": "src_planner_autoplanner_ts", "target": "src_planner_db_seedexercises", "relation": "imports_from", "confidence": "EXTRACTED", "source_file": "src\\planner\\autoPlanner.ts", "source_location": "L2", "weight": 1.0}, {"source": "src_planner_autoplanner_ts", "target": "src_planner_data_functionalmapping", "relation": "imports_from", "confidence": "EXTRACTED", "source_file": "src\\planner\\autoPlanner.ts", "source_location": "L3", "weight": 1.0}, {"source": "src_planner_autoplanner_ts", "target": "src_planner_data_goalaccessories", "relation": "imports_from", "confidence": "EXTRACTED", "source_file": "src\\planner\\autoPlanner.ts", "source_location": "L4", "weight": 1.0}, {"source": "src_planner_autoplanner_ts", "target": "autoplanner_baselinerepgoal", "relation": "contains", "confidence": "EXTRACTED", "source_file": "src\\planner\\autoPlanner.ts", "source_location": "L94", "weight": 1.0}, {"source": "src_planner_autoplanner_ts", "target": "autoplanner_getroutinesessionlabel", "relation": "contains", "confidence": "EXTRACTED", "source_file": "src\\planner\\autoPlanner.ts", "source_location": "L225", "weight": 1.0}, {"source": "src_planner_autoplanner_ts", "target": "autoplanner_getrecommendedroutinesfordays", "relation": "contains", "confidence": "EXTRACTED", "source_file": "src\\planner\\autoPlanner.ts", "source_location": "L240", "weight": 1.0}, {"source": "src_planner_autoplanner_ts", "target": "autoplanner_remapgzcltiers", "relation": "contains", "confidence": "EXTRACTED", "source_file": "src\\planner\\autoPlanner.ts", "source_location": "L256", "weight": 1.0}, {"source": "src_planner_autoplanner_ts", "target": "autoplanner_bodyregion", "relation": "contains", "confidence": "EXTRACTED", "source_file": "src\\planner\\autoPlanner.ts", "source_location": "L317", "weight": 1.0}, {"source": "src_planner_autoplanner_ts", "target": "autoplanner_normalizeexercisename", "relation": "contains", "confidence": "EXTRACTED", "source_file": "src\\planner\\autoPlanner.ts", "source_location": "L321", "weight": 1.0}, {"source": "src_planner_autoplanner_ts", "target": "autoplanner_applygoalprescription", "relation": "contains", "confidence": "EXTRACTED", "source_file": "src\\planner\\autoPlanner.ts", "source_location": "L325", "weight": 1.0}, {"source": "src_planner_autoplanner_ts", "target": "autoplanner_estimateexercisedurationseconds", "relation": "contains", "confidence": "EXTRACTED", "source_file": "src\\planner\\autoPlanner.ts", "source_location": "L340", "weight": 1.0}, {"source": "src_planner_autoplanner_ts", "target": "autoplanner_calcestimatedminutes", "relation": "contains", "confidence": "EXTRACTED", "source_file": "src\\planner\\autoPlanner.ts", "source_location": "L353", "weight": 1.0}, {"source": "src_planner_autoplanner_ts", "target": "autoplanner_isuuidv4", "relation": "contains", "confidence": "EXTRACTED", "source_file": "src\\planner\\autoPlanner.ts", "source_location": "L362", "weight": 1.0}, {"source": "src_planner_autoplanner_ts", "target": "autoplanner_islikelyprimarycompound", "relation": "contains", "confidence": "EXTRACTED", "source_file": "src\\planner\\autoPlanner.ts", "source_location": "L366", "weight": 1.0}, {"source": "src_planner_autoplanner_ts", "target": "autoplanner_normalizeroutinetype", "relation": "contains", "confidence": "EXTRACTED", "source_file": "src\\planner\\autoPlanner.ts", "source_location": "L372", "weight": 1.0}, {"source": "src_planner_autoplanner_ts", "target": "autoplanner_normalizestoredroutinetype", "relation": "contains", "confidence": "EXTRACTED", "source_file": "src\\planner\\autoPlanner.ts", "source_location": "L400", "weight": 1.0}, {"source": "src_planner_autoplanner_ts", "target": "autoplanner_inferaxis", "relation": "contains", "confidence": "EXTRACTED", "source_file": "src\\planner\\autoPlanner.ts", "source_location": "L408", "weight": 1.0}, {"source": "src_planner_autoplanner_ts", "target": "autoplanner_hassessiontag", "relation": "contains", "confidence": "EXTRACTED", "source_file": "src\\planner\\autoPlanner.ts", "source_location": "L416", "weight": 1.0}, {"source": "src_planner_autoplanner_ts", "target": "autoplanner_filterbysessionrule", "relation": "contains", "confidence": "EXTRACTED", "source_file": "src\\planner\\autoPlanner.ts", "source_location": "L431", "weight": 1.0}, {"source": "src_planner_autoplanner_ts", "target": "autoplanner_dedupeexercisesbyid", "relation": "contains", "confidence": "EXTRACTED", "source_file": "src\\planner\\autoPlanner.ts", "source_location": "L444", "weight": 1.0}, {"source": "src_planner_autoplanner_ts", "target": "autoplanner_dedupeplannedbyid", "relation": "contains", "confidence": "EXTRACTED", "source_file": "src\\planner\\autoPlanner.ts", "source_location": "L463", "weight": 1.0}, {"source": "src_planner_autoplanner_ts", "target": "autoplanner_buildvolumeexpansioncandidates", "relation": "contains", "confidence": "EXTRACTED", "source_file": "src\\planner\\autoPlanner.ts", "source_location": "L477", "weight": 1.0}, {"source": "src_planner_autoplanner_ts", "target": "autoplanner_classifyexpansionname", "relation": "contains", "confidence": "EXTRACTED", "source_file": "src\\planner\\autoPlanner.ts", "source_location": "L513", "weight": 1.0}, {"source": "src_planner_autoplanner_ts", "target": "autoplanner_classifyexpansioncandidate", "relation": "contains", "confidence": "EXTRACTED", "source_file": "src\\planner\\autoPlanner.ts", "source_location": "L527", "weight": 1.0}, {"source": "src_planner_autoplanner_ts", "target": "autoplanner_buildcategoryexpansionqueue", "relation": "contains", "confidence": "EXTRACTED", "source_file": "src\\planner\\autoPlanner.ts", "source_location": "L531", "weight": 1.0}, {"source": "src_planner_autoplanner_ts", "target": "autoplanner_expandfortimebudget", "relation": "contains", "confidence": "EXTRACTED", "source_file": "src\\planner\\autoPlanner.ts", "source_location": "L574", "weight": 1.0}, {"source": "src_planner_autoplanner_ts", "target": "autoplanner_getblueprint", "relation": "contains", "confidence": "EXTRACTED", "source_file": "src\\planner\\autoPlanner.ts", "source_location": "L665", "weight": 1.0}, {"source": "src_planner_autoplanner_ts", "target": "autoplanner_getblueprintexercises", "relation": "contains", "confidence": "EXTRACTED", "source_file": "src\\planner\\autoPlanner.ts", "source_location": "L675", "weight": 1.0}, {"source": "src_planner_autoplanner_ts", "target": "autoplanner_detectsessionindex", "relation": "contains", "confidence": "EXTRACTED", "source_file": "src\\planner\\autoPlanner.ts", "source_location": "L707", "weight": 1.0}, {"source": "src_planner_autoplanner_ts", "target": "autoplanner_picklowerbodysessionindex", "relation": "contains", "confidence": "EXTRACTED", "source_file": "src\\planner\\autoPlanner.ts", "source_location": "L711", "weight": 1.0}, {"source": "src_planner_autoplanner_ts", "target": "autoplanner_tiercapfortime", "relation": "contains", "confidence": "EXTRACTED", "source_file": "src\\planner\\autoPlanner.ts", "source_location": "L738", "weight": 1.0}, {"source": "src_planner_autoplanner_ts", "target": "autoplanner_getmaxexercisesfortime", "relation": "contains", "confidence": "EXTRACTED", "source_file": "src\\planner\\autoPlanner.ts", "source_location": "L748", "weight": 1.0}, {"source": "src_planner_autoplanner_ts", "target": "autoplanner_buildcoreblueprintbytier", "relation": "contains", "confidence": "EXTRACTED", "source_file": "src\\planner\\autoPlanner.ts", "source_location": "L764", "weight": 1.0}, {"source": "src_planner_autoplanner_ts", "target": "autoplanner_maprecentsetsbyexercise", "relation": "contains", "confidence": "EXTRACTED", "source_file": "src\\planner\\autoPlanner.ts", "source_location": "L786", "weight": 1.0}, {"source": "src_planner_autoplanner_ts", "target": "autoplanner_planexercisefromhistory", "relation": "contains", "confidence": "EXTRACTED", "source_file": "src\\planner\\autoPlanner.ts", "source_location": "L803", "weight": 1.0}, {"source": "src_planner_autoplanner_ts", "target": "autoplanner_planroutineworkoutpure", "relation": "contains", "confidence": "EXTRACTED", "source_file": "src\\planner\\autoPlanner.ts", "source_location": "L885", "weight": 1.0}, {"source": "src_planner_autoplanner_ts", "target": "autoplanner_runplannerpreflightaudit", "relation": "contains", "confidence": "EXTRACTED", "source_file": "src\\planner\\autoPlanner.ts", "source_location": "L1024", "weight": 1.0}, {"source": "src_planner_autoplanner_ts", "target": "autoplanner_generateworkout", "relation": "contains", "confidence": "EXTRACTED", "source_file": "src\\planner\\autoPlanner.ts", "source_location": "L1091", "weight": 1.0}, {"source": "autoplanner_getroutinesessionlabel", "target": "autoplanner_normalizeroutinetype", "relation": "calls", "confidence": "EXTRACTED", "source_file": "src\\planner\\autoPlanner.ts", "source_location": "L226", "weight": 1.0}, {"source": "autoplanner_normalizestoredroutinetype", "target": "autoplanner_normalizeroutinetype", "relation": "calls", "confidence": "EXTRACTED", "source_file": "src\\planner\\autoPlanner.ts", "source_location": "L402", "weight": 1.0}, {"source": "autoplanner_inferaxis", "target": "autoplanner_bodyregion", "relation": "calls", "confidence": "EXTRACTED", "source_file": "src\\planner\\autoPlanner.ts", "source_location": "L413", "weight": 1.0}, {"source": "autoplanner_hassessiontag", "target": "autoplanner_inferaxis", "relation": "calls", "confidence": "EXTRACTED", "source_file": "src\\planner\\autoPlanner.ts", "source_location": "L423", "weight": 1.0}, {"source": "autoplanner_buildvolumeexpansioncandidates", "target": "autoplanner_dedupeexercisesbyid", "relation": "calls", "confidence": "EXTRACTED", "source_file": "src\\planner\\autoPlanner.ts", "source_location": "L486", "weight": 1.0}, {"source": "autoplanner_classifyexpansioncandidate", "target": "autoplanner_classifyexpansionname", "relation": "calls", "confidence": "EXTRACTED", "source_file": "src\\planner\\autoPlanner.ts", "source_location": "L528", "weight": 1.0}, {"source": "autoplanner_buildcategoryexpansionqueue", "target": "autoplanner_classifyexpansioncandidate", "relation": "calls", "confidence": "EXTRACTED", "source_file": "src\\planner\\autoPlanner.ts", "source_location": "L540", "weight": 1.0}, {"source": "autoplanner_expandfortimebudget", "target": "autoplanner_getmaxexercisesfortime", "relation": "calls", "confidence": "EXTRACTED", "source_file": "src\\planner\\autoPlanner.ts", "source_location": "L580", "weight": 1.0}, {"source": "autoplanner_expandfortimebudget", "target": "autoplanner_calcestimatedminutes", "relation": "calls", "confidence": "EXTRACTED", "source_file": "src\\planner\\autoPlanner.ts", "source_location": "L582", "weight": 1.0}, {"source": "autoplanner_expandfortimebudget", "target": "autoplanner_buildcategoryexpansionqueue", "relation": "calls", "confidence": "EXTRACTED", "source_file": "src\\planner\\autoPlanner.ts", "source_location": "L590", "weight": 1.0}, {"source": "autoplanner_expandfortimebudget", "target": "autoplanner_normalizeexercisename", "relation": "calls", "confidence": "EXTRACTED", "source_file": "src\\planner\\autoPlanner.ts", "source_location": "L597", "weight": 1.0}, {"source": "autoplanner_getblueprintexercises", "target": "autoplanner_filterbysessionrule", "relation": "calls", "confidence": "EXTRACTED", "source_file": "src\\planner\\autoPlanner.ts", "source_location": "L679", "weight": 1.0}, {"source": "autoplanner_getblueprintexercises", "target": "autoplanner_dedupeexercisesbyid", "relation": "calls", "confidence": "EXTRACTED", "source_file": "src\\planner\\autoPlanner.ts", "source_location": "L682", "weight": 1.0}, {"source": "autoplanner_getblueprintexercises", "target": "autoplanner_remapgzcltiers", "relation": "calls", "confidence": "EXTRACTED", "source_file": "src\\planner\\autoPlanner.ts", "source_location": "L704", "weight": 1.0}, {"source": "autoplanner_picklowerbodysessionindex", "target": "autoplanner_getblueprint", "relation": "calls", "confidence": "EXTRACTED", "source_file": "src\\planner\\autoPlanner.ts", "source_location": "L723", "weight": 1.0}, {"source": "autoplanner_picklowerbodysessionindex", "target": "autoplanner_getblueprintexercises", "relation": "calls", "confidence": "EXTRACTED", "source_file": "src\\planner\\autoPlanner.ts", "source_location": "L724", "weight": 1.0}, {"source": "autoplanner_planexercisefromhistory", "target": "autoplanner_inferaxis", "relation": "calls", "confidence": "EXTRACTED", "source_file": "src\\planner\\autoPlanner.ts", "source_location": "L808", "weight": 1.0}, {"source": "autoplanner_planexercisefromhistory", "target": "autoplanner_baselinerepgoal", "relation": "calls", "confidence": "EXTRACTED", "source_file": "src\\planner\\autoPlanner.ts", "source_location": "L814", "weight": 1.0}, {"source": "autoplanner_planroutineworkoutpure", "target": "autoplanner_normalizeroutinetype", "relation": "calls", "confidence": "EXTRACTED", "source_file": "src\\planner\\autoPlanner.ts", "source_location": "L901", "weight": 1.0}, {"source": "autoplanner_planroutineworkoutpure", "target": "autoplanner_detectsessionindex", "relation": "calls", "confidence": "EXTRACTED", "source_file": "src\\planner\\autoPlanner.ts", "source_location": "L903", "weight": 1.0}, {"source": "autoplanner_planroutineworkoutpure", "target": "autoplanner_picklowerbodysessionindex", "relation": "calls", "confidence": "EXTRACTED", "source_file": "src\\planner\\autoPlanner.ts", "source_location": "L913", "weight": 1.0}, {"source": "autoplanner_planroutineworkoutpure", "target": "autoplanner_getblueprint", "relation": "calls", "confidence": "EXTRACTED", "source_file": "src\\planner\\autoPlanner.ts", "source_location": "L915", "weight": 1.0}, {"source": "autoplanner_planroutineworkoutpure", "target": "autoplanner_getblueprintexercises", "relation": "calls", "confidence": "EXTRACTED", "source_file": "src\\planner\\autoPlanner.ts", "source_location": "L917", "weight": 1.0}, {"source": "autoplanner_planroutineworkoutpure", "target": "autoplanner_calcestimatedminutes", "relation": "calls", "confidence": "EXTRACTED", "source_file": "src\\planner\\autoPlanner.ts", "source_location": "L922", "weight": 1.0}, {"source": "autoplanner_planroutineworkoutpure", "target": "autoplanner_maprecentsetsbyexercise", "relation": "calls", "confidence": "EXTRACTED", "source_file": "src\\planner\\autoPlanner.ts", "source_location": "L935", "weight": 1.0}, {"source": "autoplanner_planroutineworkoutpure", "target": "autoplanner_dedupeplannedbyid", "relation": "calls", "confidence": "EXTRACTED", "source_file": "src\\planner\\autoPlanner.ts", "source_location": "L940", "weight": 1.0}, {"source": "autoplanner_planroutineworkoutpure", "target": "autoplanner_tiercapfortime", "relation": "calls", "confidence": "EXTRACTED", "source_file": "src\\planner\\autoPlanner.ts", "source_location": "L955", "weight": 1.0}, {"source": "autoplanner_planroutineworkoutpure", "target": "autoplanner_buildcoreblueprintbytier", "relation": "calls", "confidence": "EXTRACTED", "source_file": "src\\planner\\autoPlanner.ts", "source_location": "L956", "weight": 1.0}, {"source": "autoplanner_planroutineworkoutpure", "target": "autoplanner_planexercisefromhistory", "relation": "calls", "confidence": "EXTRACTED", "source_file": "src\\planner\\autoPlanner.ts", "source_location": "L979", "weight": 1.0}, {"source": "autoplanner_planroutineworkoutpure", "target": "autoplanner_applygoalprescription", "relation": "calls", "confidence": "EXTRACTED", "source_file": "src\\planner\\autoPlanner.ts", "source_location": "L980", "weight": 1.0}, {"source": "autoplanner_planroutineworkoutpure", "target": "autoplanner_getmaxexercisesfortime", "relation": "calls", "confidence": "EXTRACTED", "source_file": "src\\planner\\autoPlanner.ts", "source_location": "L988", "weight": 1.0}, {"source": "autoplanner_planroutineworkoutpure", "target": "autoplanner_buildvolumeexpansioncandidates", "relation": "calls", "confidence": "EXTRACTED", "source_file": "src\\planner\\autoPlanner.ts", "source_location": "L997", "weight": 1.0}, {"source": "autoplanner_planroutineworkoutpure", "target": "autoplanner_expandfortimebudget", "relation": "calls", "confidence": "EXTRACTED", "source_file": "src\\planner\\autoPlanner.ts", "source_location": "L1011", "weight": 1.0}, {"source": "autoplanner_runplannerpreflightaudit", "target": "autoplanner_isuuidv4", "relation": "calls", "confidence": "EXTRACTED", "source_file": "src\\planner\\autoPlanner.ts", "source_location": "L1035", "weight": 1.0}, {"source": "autoplanner_generateworkout", "target": "autoplanner_normalizeroutinetype", "relation": "calls", "confidence": "EXTRACTED", "source_file": "src\\planner\\autoPlanner.ts", "source_location": "L1099", "weight": 1.0}, {"source": "autoplanner_generateworkout", "target": "autoplanner_runplannerpreflightaudit", "relation": "calls", "confidence": "EXTRACTED", "source_file": "src\\planner\\autoPlanner.ts", "source_location": "L1107", "weight": 1.0}, {"source": "autoplanner_generateworkout", "target": "autoplanner_planroutineworkoutpure", "relation": "calls", "confidence": "EXTRACTED", "source_file": "src\\planner\\autoPlanner.ts", "source_location": "L1130", "weight": 1.0}]}